wridgets/__init__.py
wridgets/app.py
wridgets/plotting.py
wridgets/utils.py
wridgets/version.py
wridgets/wridgets.py
wridgets-0.1.8.dist-info/LICENSE
wridgets-0.1.8.dist-info/METADATA
wridgets-0.1.8.dist-info/WHEEL
wridgets-0.1.8.dist-info/top_level.txt
wridgets-0.1.8.dist-info/RECORD
