Metadata-Version: 2.1
Name: wridgets
Version: 0.1.8
Summary: Wrapper around ipywidgets
Home-page: UNKNOWN
Author: Stelios Papadopoulos
Author-email: stelios@spapa.us
License: UNKNOWN
Platform: UNKNOWN
License-File: LICENSE
Requires-Dist: ipywidgets
Requires-Dist: numpy
